setup.py
pyoctopart/__init__.py
pyoctopart/exceptions.py
pyoctopart/octopart.py
pyoctopart.egg-info/PKG-INFO
pyoctopart.egg-info/SOURCES.txt
pyoctopart.egg-info/dependency_links.txt
pyoctopart.egg-info/not-zip-safe
pyoctopart.egg-info/pbr.json
pyoctopart.egg-info/requires.txt
pyoctopart.egg-info/top_level.txt