Metadata-Version: 1.1
Name: pyoctopart
Version: 0.6.3
Summary: Python library to connect to Octopart
Home-page: https://github.com/guyzmo/pyoctopart
Author: Bernard `Guyzmo` Pratz
Author-email: pyoctopart@m0g.net
License: GPLv3
Keywords: download tv show
Platform: UNKNOWN
Classifier: Development Status :: 4 - Beta
Classifier: License :: OSI Approved
Classifier: Operating System :: Unix
